{
    "key": "group_5fba9092307df",
    "title": "Uitzending gemist (Vimeo)",
    "fields": [
        {
            "key": "field_5fba9099c14e2",
            "label": "Vimeo client ID",
            "name": "vimeo_client_id",
            "type": "password",
            "instructions": "",
            "required": 0,
            "conditional_logic": 0,
            "wrapper": {
                "width": "",
                "class": "",
                "id": ""
            },
            "placeholder": "",
            "prepend": "",
            "append": ""
        },
        {
            "key": "field_5fba90b3e0bbc",
            "label": "Vimeo client secret",
            "name": "vimeo_client_secret",
            "type": "password",
            "instructions": "",
            "required": 0,
            "conditional_logic": 0,
            "wrapper": {
                "width": "",
                "class": "",
                "id": ""
            },
            "placeholder": "",
            "prepend": "",
            "append": ""
        },
        {
            "key": "field_5fba90d3e0bbd",
            "label": "Vimeo access token",
            "name": "vimeo_access_token",
            "type": "password",
            "instructions": "",
            "required": 0,
            "conditional_logic": 0,
            "wrapper": {
                "width": "",
                "class": "",
                "id": ""
            },
            "placeholder": "",
            "prepend": "",
            "append": ""
        }
    ],
    "location": [
        [
            {
                "param": "options_page",
                "operator": "==",
                "value": "tv-instellingen"
            }
        ]
    ],
    "menu_order": 0,
    "position": "normal",
    "style": "default",
    "label_placement": "top",
    "instruction_placement": "label",
    "hide_on_screen": "",
    "active": true,
    "description": "",
    "modified": 1607366213
}